turingproject/__init__.py
turingproject/calculator.py
turingproject-0.0.3.dist-info/LICENSE
turingproject-0.0.3.dist-info/WHEEL
turingproject-0.0.3.dist-info/METADATA
turingproject-0.0.3.dist-info/RECORD
