Metadata-Version: 2.1
Name: turingproject
Version: 0.0.3
Summary: A small example package
Author-email: Vitalijus Kiubis <vitalijus.kiubis@gmail.com>
Requires-Python: >=3.7
Classifier: License :: OSI Approved :: MIT License
